mgsutils/__init__.py
mgsutils/plots.py
mgsutils-1.0.0.dist-info/DESCRIPTION.rst
mgsutils-1.0.0.dist-info/METADATA
mgsutils-1.0.0.dist-info/RECORD
mgsutils-1.0.0.dist-info/WHEEL
mgsutils-1.0.0.dist-info/metadata.json
mgsutils-1.0.0.dist-info/top_level.txt
