Metadata-Version: 2.0
Name: mgsutils
Version: 1.0.0
Summary: Model of Earth atmosphere absorption and transmission vs. wavelength and location on Earth.
Home-page: https://github.com/scivision/mgs-utils
Author: Michael Hirsch, Ph.D
Author-email: UNKNOWN
License: UNKNOWN
Platform: UNKNOWN
Classifier: Intended Audience :: Science/Research
Classifier: Development Status :: 4 - Beta
Classifier: License :: OSI Approved :: GNU General Public License v3 or later (GPLv3+)
Classifier: Topic :: Scientific/Engineering :: Atmospheric Science
Classifier: Programming Language :: Python :: 3.6
